zernikepolpy/__init__.py
zernikepolpy/zernikepolpy.py
zernikepolpy-0.1.0.dist-info/licenses/COPYING
zernikepolpy-0.1.0.dist-info/WHEEL
zernikepolpy-0.1.0.dist-info/METADATA
zernikepolpy-0.1.0.dist-info/RECORD
