Metadata-Version: 2.4
Name: zernikepolpy
Version: 0.1.0
Summary: Utilities and Python wrappers for Zernike Polynomials.
Keywords: math,polynom
Author-email: Thorsten Alteholz <zernikepolpy@alteholz.dev>
Maintainer-email: Thorsten Alteholz <zernikepolpy@alteholz.dev>
Requires-Python: >=3.13
Classifier: License :: OSI Approved :: MIT License
Classifier: Development Status :: 4 - Beta
Classifier: Intended Audience :: Education
Classifier: Intended Audience :: Science/Research
Classifier: License :: OSI Approved :: MIT License
Classifier: Operating System :: OS Independent
Classifier: Programming Language :: Python
Classifier: Programming Language :: Python :: 3
Classifier: Programming Language :: Python :: 3.13
Classifier: Programming Language :: Python :: Implementation :: CPython
License-File: COPYING
Requires-Dist: numpy >= 2.0.2
Requires-Dist: gmpy2
Requires-Dist: tox ; extra == "dev"
Requires-Dist: pytest ; extra == "dev"
Requires-Dist: pytest-benchmark ; extra == "dev"
Requires-Dist: tox ; extra == "test"
Requires-Dist: pytest ; extra == "test"
Requires-Dist: pytest-benchmark ; extra == "test"
Provides-Extra: dev
Provides-Extra: test
